pyframe3dd
