Metadata-Version: 2.1
Name: pyframe3dd
Version: 0.0.2.1
Summary: estructural analysis using frame3dd
Home-page: https://www.illarisoft.com/
Author: Edwin Pareja
Author-email: edwinsaulpm@gmail.com
License: UNKNOWN
Platform: UNKNOWN
License-File: LICENSE
